visualwebarena/test_raw.json
visualwebarena/agent/__init__.py
visualwebarena/agent/agent.py
visualwebarena/browser_env/__init__.py
visualwebarena/browser_env/actions.py
visualwebarena/browser_env/async_envs.py
visualwebarena/browser_env/auto_login.py
visualwebarena/browser_env/constants.py
visualwebarena/browser_env/env_config.py
visualwebarena/browser_env/envs.py
visualwebarena/browser_env/helper_functions.py
visualwebarena/browser_env/processors.py
visualwebarena/browser_env/py.typed
visualwebarena/browser_env/trajectory.py
visualwebarena/browser_env/utils.py
visualwebarena/coco_images/000000000285.jpg
visualwebarena/coco_images/000000022371.jpg
visualwebarena/coco_images/000000023781.jpg
visualwebarena/coco_images/000000024567.jpg
visualwebarena/coco_images/000000029675.jpg
visualwebarena/coco_images/000000029984.jpg
visualwebarena/coco_images/000000039551.jpg
visualwebarena/coco_images/000000048153.jpg
visualwebarena/coco_images/000000048396.jpg
visualwebarena/coco_images/000000048924.jpg
visualwebarena/coco_images/000000050331.jpg
visualwebarena/coco_images/000000058539.jpg
visualwebarena/coco_images/000000058705.jpg
visualwebarena/coco_images/000000060899.jpg
visualwebarena/coco_images/000000064574.jpg
visualwebarena/coco_images/000000064718.jpg
visualwebarena/coco_images/000000066771.jpg
visualwebarena/coco_images/000000084477.jpg
visualwebarena/coco_images/000000097278.jpg
visualwebarena/coco_images/000000102805.jpg
visualwebarena/coco_images/000000136772.jpg
visualwebarena/coco_images/000000161032.jpg
visualwebarena/coco_images/000000162415.jpg
visualwebarena/coco_images/000000163257.jpg
visualwebarena/coco_images/000000163682.jpg
visualwebarena/coco_images/000000166768.jpg
visualwebarena/coco_images/000000167240.jpg
visualwebarena/coco_images/000000167353.jpg
visualwebarena/coco_images/000000172595.jpg
visualwebarena/coco_images/000000173008.jpg
visualwebarena/coco_images/000000175443.jpg
visualwebarena/coco_images/000000176232.jpg
libvisualwebarena-0.0.15.dist-info/LICENSE
libvisualwebarena-0.0.15.dist-info/METADATA
libvisualwebarena-0.0.15.dist-info/WHEEL
libvisualwebarena-0.0.15.dist-info/top_level.txt
libvisualwebarena-0.0.15.dist-info/RECORD
