Metadata-Version: 2.1
Name: libvisualwebarena
Version: 0.0.15
Summary: This is an unofficial, use-at-your-own risks port of the visualwebarena benchmark, for use as a standalone library package.
Requires-Python: <4,>=3.7
License-File: LICENSE
Requires-Dist: gymnasium
Requires-Dist: playwright ~=1.39
Requires-Dist: Pillow
Requires-Dist: evaluate
Requires-Dist: openai >=1
Requires-Dist: types-tqdm
Requires-Dist: tiktoken
Requires-Dist: aiolimiter
Requires-Dist: beartype ==0.12.0
Requires-Dist: flask
Requires-Dist: nltk
Requires-Dist: text-generation
Requires-Dist: transformers
Requires-Dist: scikit-image >=0.16
